fluxem_core/__init__.py
fluxem_core/constant/__init__.py
fluxem_core/constant/search_constants.py
fluxem_core/dto/__init__.py
fluxem_core/dto/request/__init__.py
fluxem_core/dto/request/filter_criteria.py
fluxem_core/dto/request/filter_group.py
fluxem_core/dto/request/filter_operator.py
fluxem_core/dto/request/search_request.py
fluxem_core/dto/request/sort_criteria.py
fluxem_core/dto/request/sort_direction.py
fluxem_core/dto/response/__init__.py
fluxem_core/dto/response/api_error_response.py
fluxem_core/dto/response/api_response.py
fluxem_core/dto/response/flexible_api_response.py
fluxem_core/dto/response/flexible_response_data.py
fluxem_core/dto/response/flexible_search_response.py
fluxem_core/dto/response/paginated_data.py
fluxem_core/dto/response/pagination_metadata.py
fluxem_core/dto/response/response_meta.py
fluxem_core/dto/response/search_response.py
fluxem_core/exceptions/__init__.py
fluxem_core/exceptions/fluxem_core_exception.py
fluxem_core/exceptions/invalid_field_exception.py
fluxem_core/exceptions/invalid_operator_exception.py
fluxem_core/exceptions/invalid_value_exception.py
fluxem_core/exceptions/search_engine_exception.py
fluxem_core/search/__init__.py
fluxem_core/search/abstract_search_service.py
fluxem_core/search/operator_applier.py
fluxem_core/search/order_builder.py
fluxem_core/search/predicate_builder.py
fluxem_core/search/search_engine.py
fluxem_core/util/__init__.py
fluxem_core/util/field_validator.py
fluxem_core/util/value_converter.py
fluxem_core-1.0.2.dist-info/METADATA
fluxem_core-1.0.2.dist-info/WHEEL
fluxem_core-1.0.2.dist-info/licenses/LICENSE
fluxem_core-1.0.2.dist-info/RECORD
