Metadata-Version: 2.4
Name: fluxem-core
Version: 1.0.2
Summary: Librería empresarial completa para proyectos Python con DTOs estándar, motor de búsqueda avanzada con SQLAlchemy y utilidades comunes
License: MIT
License-File: LICENSE
Keywords: search,filter,pagination,sqlalchemy,fastapi,api
Author: Fluxem Development Team
Author-email: dev@fluxem.com
Requires-Python: >=3.11,<4.0
Classifier: Development Status :: 4 - Beta
Classifier: Intended Audience :: Developers
Classifier: License :: OSI Approved :: MIT License
Classifier: Programming Language :: Python :: 3
Classifier: Programming Language :: Python :: 3.11
Classifier: Programming Language :: Python :: 3.12
Classifier: Programming Language :: Python :: 3.13
Classifier: Programming Language :: Python :: 3.14
Classifier: Topic :: Software Development :: Libraries :: Python Modules
Requires-Dist: pydantic (>=2.5.0,<3.0.0)
Requires-Dist: sqlalchemy (>=2.0.0,<3.0.0)
Requires-Dist: typing-extensions (>=4.8.0,<5.0.0)
Project-URL: Documentation, https://fluxem-core-py.readthedocs.io
Project-URL: Homepage, https://github.com/fluxem-sas/fluxem-core-py
Project-URL: Repository, https://github.com/fluxem-sas/fluxem-core-py
